GPTManager/Assistant.py
GPTManager/Thread.py
GPTManager/__init__.py
GPTManager-0.0.2.dist-info/LICENSE
GPTManager-0.0.2.dist-info/METADATA
GPTManager-0.0.2.dist-info/WHEEL
GPTManager-0.0.2.dist-info/top_level.txt
GPTManager-0.0.2.dist-info/RECORD
